HoloAI/HoloAI.py
HoloAI/__init__.py
HoloAI/HAIBaseConfig/BaseConfig.py
HoloAI/HAIBaseConfig/__init__.py
HoloAI/HAIConfigs/AnthropicConfig.py
HoloAI/HAIConfigs/GoogleConfig.py
HoloAI/HAIConfigs/GroqConfig.py
HoloAI/HAIConfigs/OpenAIConfig.py
HoloAI/HAIConfigs/__init__.py
HoloAI/HAIConfigs/xAIConfig.py
HoloAI/HAIUtils/HAIUtils.py
HoloAI/HAIUtils/__init__.py
holoai-0.5.2.dist-info/METADATA
holoai-0.5.2.dist-info/WHEEL
holoai-0.5.2.dist-info/top_level.txt
holoai-0.5.2.dist-info/RECORD
