Metadata-Version: 2.4
Name: HoloAI
Version: 0.5.2
Summary: Modular, provider-agnostic AI framework for multi-model orchestration, agent workflows, and vision.
Author: Tristan McBride Sr.
Author-email: "Tristan McBride Sr." <142635792+TristanMcBrideSr@users.noreply.github.com>
Maintainer-email: "Tristan McBride Sr." <142635792+TristanMcBrideSr@users.noreply.github.com>
License-Expression: Apache-2.0
Project-URL: Homepage, https://github.com/TristanMcBrideSr
Keywords: AI,AI Client,Agents,Skills,Tools,Learning,Productivity,Automation
Classifier: Programming Language :: Python :: 3
Classifier: Operating System :: OS Independent
Classifier: Intended Audience :: Developers
Requires-Python: >=3.10
Requires-Dist: openai
Requires-Dist: groq
Requires-Dist: google-genai
Requires-Dist: anthropic
Requires-Dist: HoloLink
Requires-Dist: HoloSync
Requires-Dist: HoloMem
Requires-Dist: HoloLrn
Requires-Dist: HoloLog
Requires-Dist: HoloViro
Requires-Dist: HoloRelay
Requires-Dist: HoloCapture
Requires-Dist: HoloEcho
Requires-Dist: SyncLink
Requires-Dist: SynMem
Requires-Dist: SynLrn
Requires-Dist: BitSig
Requires-Dist: MediaCapture
Requires-Dist: AgentToAgent
Requires-Dist: python-dotenv
Requires-Dist: requests
Requires-Dist: opencv-python
Requires-Dist: Pillow
Requires-Dist: gguf-parser
Requires-Dist: numpy
Requires-Dist: pdfplumber
Requires-Dist: python-docx
Dynamic: author
